{"examples_example_3d_pouch.md":"CUAv6Mdu","examples_example_battery.md":"Mpk_Fsi_","examples_example_cycle.md":"C9pvtWz0","examples_example_sei.md":"BDBNQhFm","extras_refs.md":"B06TzF5j","index.md":"BFUgkKKS","manuals_api_documentation_highlevel.md":"CZZIJoTc","manuals_api_documentation_introduction.md":"CXY3h4G1","manuals_contribution_contribution.md":"BITswT4E","manuals_contribution_jutul_integration.md":"zTdpCw4Y","manuals_user_guide_control_params.md":"CG0D9ySM","manuals_user_guide_geometries.md":"tOzprQ6c","manuals_user_guide_getting_started.md":"DNQfLgE5","manuals_user_guide_grid_params.md":"BTCjgqtW","manuals_user_guide_hdf5_output.md":"0w5NYQN-","manuals_user_guide_installation.md":"B3AwNbM0","manuals_user_guide_introduction.md":"BzKsoshN","manuals_user_guide_json_input.md":"BLpg7ebK","manuals_user_guide_non_scalar_input_quantities.md":"D9EN6obU","manuals_user_guide_public_api.md":"CAMAM86X","manuals_user_guide_pxd_model.md":"BF-gqPQn","manuals_user_guide_ramp_up.md":"grNEyPY8","manuals_user_guide_simulation_dependent_input.md":"DsB0maVN","manuals_user_guide_simulation_output.md":"CYV4zFXT","manuals_user_guide_terminology.md":"jDY7XnKq","tutorials_1_run_a_simulation.md":"I2MU5U87","tutorials_1_useful_tools.md":"Bri7HHAR","tutorials_2_select_a_model.md":"DVxAooK6","tutorials_3_handle_outputs.md":"MHUIyejm","tutorials_4_handle_cell_parameters.md":"Bax8hS4d","tutorials_5_handle_cycling_protocols.md":"BD_McmOG","tutorials_6_compute_cell_kpis.md":"C64Wp4Qf","tutorials_7_run_parameter_sweep.md":"B8peJ1bR"}
